csv_to_dot/__init__.py
csv_to_dot/csv_to_dot.py
csv_to_dot/resources/__init__.py
csv_to_dot/resources/graf.dot.j2
entry_points_csv_to_dot/__init__.py
entry_points_csv_to_dot/csv_to_dot.py
csv_to_dot-0.0.1.dist-info/LICENCE
csv_to_dot-0.0.1.dist-info/METADATA
csv_to_dot-0.0.1.dist-info/WHEEL
csv_to_dot-0.0.1.dist-info/entry_points.txt
csv_to_dot-0.0.1.dist-info/top_level.txt
csv_to_dot-0.0.1.dist-info/RECORD
