Metadata-Version: 2.1
Name: csv-to-dot
Version: 0.0.1
Summary: Convert a 2 columns CSV file to a .dot, who can be converted with Graphviz to .jpg, .ps, ...
Home-page: https://github.com/Mindbaz/python-csv-to-dot
Author: Valentin Henon
Author-email: vhenon@mindbaz.com
License: GPLv3
Keywords: graphviz
Classifier: Programming Language :: Python :: 3.9
Requires-Python: >=3.7
License-File: LICENCE
Requires-Dist: Jinja2
